asi4py/__init__.py
asi4py/asecalc.py
asi4py/dm.py
asi4py/pyasi.py
asi4py-1.4.5.dist-info/licenses/LICENSE
asi4py-1.4.5.dist-info/METADATA
asi4py-1.4.5.dist-info/WHEEL
asi4py-1.4.5.dist-info/top_level.txt
asi4py-1.4.5.dist-info/RECORD
