Metadata-Version: 2.4
Name: asi4py
Version: 1.4.5
Summary: A Python wrapper for Atomic Simulation Interface API
Author-email: Pavel Stishenko <pstishenko@gmail.com>, Gabriel Bramley <BramleyG@cardiff.ac.uk>
License: MIT License
Project-URL: Homepage, https://gitlab.com/pvst/asi
Project-URL: Bug Tracker, https://gitlab.com/pvst/asi/-/issues
Classifier: Programming Language :: Python :: 3
Classifier: License :: OSI Approved :: MIT License
Classifier: Operating System :: OS Independent
Requires-Python: >=3.7
License-File: LICENSE
Requires-Dist: ase==3.24.0
Requires-Dist: scalapack4py==0.2.0
Dynamic: license-file
